smogn/__init__.py
smogn/box_plot_stats.py
smogn/dist_metrics.py
smogn/over_sampling.py
smogn/phi.py
smogn/phi_ctrl_pts.py
smogn/smoter.py
smogn-0.1.2.dist-info/LICENSE
smogn-0.1.2.dist-info/METADATA
smogn-0.1.2.dist-info/WHEEL
smogn-0.1.2.dist-info/top_level.txt
smogn-0.1.2.dist-info/RECORD
