Metadata-Version: 2.1
Name: smogn
Version: 0.1.2
Summary: A Python implementation of Synthetic Minority Over-Sampling Technique for Regression with Gaussian Noise (SMOGN)
Home-page: https://github.com/nickkunz/smogn
Author: Nick Kunz
Author-email: nick.kunz@columbia.edu
License: UNKNOWN
Keywords: smote,over-sampling,synthetic data,imbalanced data,pre-processing,regression
Platform: UNKNOWN
Classifier: Programming Language :: Python :: 3
Classifier: Intended Audience :: Developers
Classifier: Intended Audience :: Science/Research
Classifier: Intended Audience :: Education
Classifier: Topic :: Scientific/Engineering
Classifier: Topic :: Scientific/Engineering :: Mathematics
Classifier: Topic :: Scientific/Engineering :: Artificial Intelligence
Classifier: License :: OSI Approved :: GNU General Public License v3 (GPLv3)
